{
  "slug": "taking-charge-of-your-fertility",
  "title": "Taking Charge of Your Fertility",
  "author": "Toni Weschler",
  "category": "Health",
  "subtopics": "fertility, women's health, family planning",
  "year": "1995",
  "datelineLeft": "BOOK SUMMARY",
  "datelineRight": "HEALTH",
  "motif": "custom",
  "titlePos": "bottom",
  "titleWeight": 300,
  "titleSize": 320,
  "titleTransform": "none",
  "lines": ["Taking Charge", "of Your Fertility"],
  "subline": "The definitive guide to natural birth control and pregnancy achievement.",
  "sublinePos": "subline-top",
  "accent": "brand-top",
  "brandMark": "FAM",
  "pill": "28 DAYS",
  "pillPos": "top",
  "redRule": "none",
  "customHTML": "<svg viewBox=\"0 0 1600 2400\" preserveAspectRatio=\"xMidYMid slice\" style=\"position:absolute;inset:0;width:100%;height:100%\">\n  <!-- A basal body temperature chart: 28 days of temperature readings. A clear red line shows the biphasic pattern (low, then spike at ovulation, then sustained high). The spike day is the only red. -->\n  <g transform=\"translate(800 1100)\" fill=\"none\">\n    <!-- Frame -->\n    <line x1=\"-560\" y1=\"-380\" x2=\"-560\" y2=\"220\" stroke=\"#4c4c4c\" stroke-width=\"1\"/>\n    <line x1=\"-560\" y1=\"220\" x2=\"560\" y2=\"220\" stroke=\"#4c4c4c\" stroke-width=\"1\"/>\n    <!-- Day labels -->\n    <g fill=\"#4c4c4c\" font-family=\"'Sui','Söhne','Inter',system-ui,sans-serif\" font-size=\"11\" font-weight=\"500\" letter-spacing=\"0.18em\" text-anchor=\"middle\">\n      <text x=\"-540\" y=\"250\">1</text>\n      <text x=\"-340\" y=\"250\">7</text>\n      <text x=\"-140\" y=\"250\">14</text>\n      <text x=\"60\" y=\"250\">21</text>\n      <text x=\"260\" y=\"250\">28</text>\n    </g>\n    <!-- Y axis -->\n    <text x=\"-580\" y=\"-380\" text-anchor=\"end\" font-family=\"'Sui','Söhne','Inter',system-ui,sans-serif\" font-size=\"11\" font-weight=\"500\" letter-spacing=\"0.18em\" fill=\"#4c4c4c\">99.0°</text>\n    <text x=\"-580\" y=\"-180\" text-anchor=\"end\" font-family=\"'Sui','Söhne','Inter',system-ui,sans-serif\" font-size=\"11\" font-weight=\"500\" letter-spacing=\"0.18em\" fill=\"#4c4c4c\">98.0°</text>\n    <text x=\"-580\" y=\"220\" text-anchor=\"end\" font-family=\"'Sui','Söhne','Inter',system-ui,sans-serif\" font-size=\"11\" font-weight=\"500\" letter-spacing=\"0.18em\" fill=\"#4c4c4c\">97.0°</text>\n    <text x=\"-580\" y=\"60\" text-anchor=\"end\" font-family=\"'Sui','Söhne','Inter',system-ui,sans-serif\" font-size=\"11\" font-weight=\"500\" letter-spacing=\"0.18em\" fill=\"#4c4c4c\">97.6°</text>\n    <!-- Reference lines -->\n    <line x1=\"-560\" y1=\"60\" x2=\"560\" y2=\"60\" stroke=\"#4c4c4c\" stroke-width=\"1\" stroke-dasharray=\"3 4\" opacity=\"0.6\"/>\n    <text x=\"540\" y=\"50\" text-anchor=\"end\" font-family=\"'Sui','Söhne','Inter',system-ui,sans-serif\" font-size=\"11\" font-weight=\"500\" letter-spacing=\"0.18em\" fill=\"#4c4c4c\">COVER LINE</text>\n    <!-- Pre-ovulation temperature — flat low, ash -->\n    <path d=\"M-540 120 L -460 130 L -380 110 L -300 120 L -220 130 L -140 100\" stroke=\"#cccccc\" stroke-width=\"2\"/>\n    <!-- The OVULATION SPIKE — RED, sharp rise at day 14 -->\n    <path d=\"M-140 100 L -100 -20 L -60 0 L -20 -10 L 20 -20 L 60 -40 L 100 -50 L 140 -40 L 180 -50 L 220 -40 L 260 -30 L 300 -40 L 340 -30 L 380 -20 L 420 -10 L 460 -20 L 500 -10 L 540 0\" stroke=\"#fc1c46\" stroke-width=\"3\"/>\n    <!-- Markers -->\n    <g fill=\"#cccccc\">\n      <circle cx=\"-540\" cy=\"120\" r=\"3\"/><circle cx=\"-460\" cy=\"130\" r=\"3\"/><circle cx=\"-380\" cy=\"110\" r=\"3\"/>\n      <circle cx=\"-300\" cy=\"120\" r=\"3\"/><circle cx=\"-220\" cy=\"130\" r=\"3\"/><circle cx=\"-140\" cy=\"100\" r=\"3\"/>\n    </g>\n    <!-- The ovulation marker — red dot at the spike -->\n    <circle cx=\"-100\" cy=\"-20\" r=\"7\" fill=\"#fc1c46\"/>\n    <text x=\"-100\" y=\"-50\" text-anchor=\"middle\" font-family=\"'Sui','Söhne','Inter',system-ui,sans-serif\" font-size=\"13\" font-weight=\"500\" letter-spacing=\"0.18em\" fill=\"#fc1c46\">OVULATION</text>\n  </g>\n</svg>",
  "rationale": "A 28-day BBT (basal body temperature) chart: ash curve in the follicular phase, then a sharp red spike at day 14 (ovulation) and a sustained red plateau. The book is THE chart that taught millions of women to read their cycle. 320px title sits at the bottom. The single red = the spike and the post-ovulation high."
}
