{
  "id": "anxiety-at-work",
  "title": "Anxiety at Work",
  "author": "",
  "source": "rsvp-original",
  "type": "summary",
  "addedAt": 1781599818611,
  "rewrittenAt": 1781603404517,
  "chapters": [
    {
      "title": "Unchecked workplace anxiety can spiral into serious mental illness",
      "text": "Anxiety is a persistent, intense, and overpowering fear and dread about certain occurrences. It leads to workplace errors, agitation, and general unwellness — a significant issue many employees and employers must confront today.\n\nPeople sometimes think worry, stress, and anxiety describe the same thing, but they have different meanings even when used together. Worry is a mental process involving repetitive, nagging thoughts, usually focused on a specific threat — fear of losing a job or wondering if you will get sick. Stress appears when things change and the body reacts physically, mentally, or emotionally. Anxiety affects both body and mind and can become a mental disorder in severe cases.\n\nEmployee anxiety is prevalent in companies, producing a rise in workplace concerns since nervous individuals are less motivated and less confident in their abilities.\n\nWhether anxiety comes from growing discontent with workplace practices or from the mind itself, one thing is certain: it should not be taken lightly.\n\nThis summary explains the need to pay more attention to people and their behavior and the importance of prioritizing welfare. In subsequent chapters, you will find more on seven pressing issues — overwhelming workloads, peer-to-peer learning, perfectionism, discourse, exclusion, and marginalization — that mostly cause anxiety in workplaces, plus strategies to help organizations tackle them successfully.",
      "wordCount": 213
    },
    {
      "title": "Leaders must actively protect employee mental health",
      "text": "Despite their prevalence, employees rarely discuss workplace worries openly. People with anxiety are often encouraged to hide it, which frequently results in depression and leads to what is known as the Duck Syndrome.\n\nThe term Duck Syndrome was first used at Stanford University to describe hardworking students who appear fine on the surface — gliding like ducks on water with effortless elegance. Beneath the surface, they paddle furiously to keep up.\n\nTake Chloe, for instance. She built a decent career after high school, and her manager saw potential because she was hardworking and often smiled. Behind the smile was a young woman wondering why she had to go the extra mile. Coworkers had better schooling, wonderful internships, and time to vacation and party. Chloe became overwhelmed. Afraid she was suffering from anxiety, she confided in her employer, who dismissed it and assured her that feeling overwhelmed was normal. Chloe could not take it anymore; she stopped going to work and never returned to inform anyone.\n\nAnxiety increases our risk of self-doubt, especially when we work in places where we are the minority.\n\nSimilar to Chloe's experience, some individuals grapple with overwhelming emotions for an extended period and become adept at concealing symptoms.\n\nAlthough anxiety has received more media attention, stigma still pervades the workplace, discouraging most people from discussing struggles beyond their immediate circle. The solution lies heavily with leaders, managers, and employers who must be actively involved in workers' welfare.\n\nLeaders who help staff overcome challenges may reap significant benefits — a healthier environment and a team dedicated to growth. Employees facing anxiety should be encouraged to seek help through employee assistance programs or certified counselors. Formal support programs and proactive management techniques can help people access the help they require.\n\nDid you know? According to the Anxiety and Depression Association of America (ADAA), anxiety disorders are the most common mental illness in the U.S.",
      "wordCount": 316
    },
    {
      "title": "Job insecurity is the uncertainty that haunts modern workers",
      "text": "Many workers over-commit to availability. They check phones constantly, even on vacation, to avoid being laid off. Fear drives the reaction.\n\nAssigning the appropriate people to the right responsibilities helps overcome uncertainty in teams.\n\nUncertainty increases when managers at all levels fail to communicate clearly and consistently about business difficulties. The best a manager can do is convey what they know about challenges, what the company is doing to solve them, and how those issues may affect the team and its objectives. That brings workers onboard about the current situation and how they can contribute.\n\nTeam leaders need to ensure members feel involved and relevant to reach their quota and alleviate uncertainty. Here are suggestions to encourage participation:\n\nIt's okay not to have all the answers\n\nEncourage staff to know it is fine not to have the answer to every inquiry and that they must sometimes brainstorm — but not under duress. Enhance team growth by offering relevant information and allowing members to examine their future and make educated choices together.\n\nLoosen your grip in tough times\n\nDuring difficulty, be more flexible than strict. Recognize challenges and stay with the team every step of the way.\n\nEnsure everyone knows what's expected of them\n\nDo not assume employees know what to do. Even when they do, remind them constantly. Focus on short-term objectives and emphasize collaboration.\n\nFocus on what can be controlled\n\nUncontrollable circumstances affect performance and the future of a team or business. Fear of what we cannot change causes anxiety. Effective leadership helps employees accept what they cannot change and focus on what they can.\n\nHave a bias to action\n\nWhen a team is action-oriented, employees make better decisions and progress. People in these cultures do not debate endlessly whether their strategy is the only logical one; they execute.\n\nOffer constructive feedback\n\nConstructive feedback builds on one-on-one performance and development dialogues. It is vital in lowering anxiety and deserves its own strategy. Keep reminding employees they can do better.",
      "wordCount": 330
    },
    {
      "title": "Unsustainable workloads breed resentment and burnout",
      "text": "Most company strategies focus on repairing the individual rather than addressing fundamental problems with workload and management.\n\nA defined path helps everyone set objectives. Managers can help overwhelmed employees by breaking tasks into manageable chunks and assisting them in making clear plans. Leaders must also rotate tasks because concentrating work on one person may save money short term but is not sustainable. Workplaces with shifts tend to be more productive because rotation tracks development and promotes healthy rivalry.\n\nAdequate resources help employees pay more attention to a task and get it done successfully.\n\nOrganizations nowadays encourage peers to assist one another with daily activities, networking, and educational opportunities. Peer-to-peer learning is distributed labor where tasks are assigned across colleagues. Internal network marketplaces and peer-learning workshops are common mechanisms many businesses use to exchange knowledge and skills.\n\nFormalizing peer-to-peer learning might help workers feel more confident by outlining best practices to help a team learn from one another and from peers around the company. Three methods exist to do this effectively:\n\n• Appoint a mediator. Assign someone to arrange and moderate peer-learning sessions in person or online.\n• Create a safe space. Encourage people to ask questions and share ideas. Enlist experts from other departments.\n• Keep it practical. Participation and learning are more successful when sessions address contemporary concerns.\n\nIn today's uncertain workplace landscape, future leaders must exhibit greater attentiveness to employee growth and well-being.",
      "wordCount": 235
    },
    {
      "title": "Perfectionism is an anxiety engine, not a virtue",
      "text": "Perfectionism is not a sensible aspiration to do things right; it is a corrosive desire to look faultless, and it frequently pushes others to do the same.\n\nPerfectionists experience greater levels of stress, burnout, and anxiety. They may waste so much time fiddling or deciding on a plan of action that they end up doing very little.\n\nA critical distinction exists between detrimental perfectionism and healthy striving, which lies in establishing reasonable standards and recognizing when something is \"good enough.\" Someone obsessed with being perfect seeks a lot of advice, does not take risks, and regards most choices as if they were life or death.\n\nA technique for overcoming perfectionism is replacing self-critical beliefs with more realistic and beneficial statements that reward positive behavior.\n\nPeople with perfectionist inclinations might benefit from strategies that include:\n\nSeeing failure as a chance for growth\n\nIf we fail, we must learn from errors and improve our efforts. We can recognize what went awry when we understand what happened.\n\nTeaming them up\n\nWhen you have someone obsessed with perfection in your company, one of the greatest ways to assist them is to team them up with others. Perfectionists prefer to work alone because they believe others cannot accomplish what they desire. When placed on a team, however, they have little option but to collaborate and learn.\n\nLeaders should not promote a work atmosphere where certain employees seem invisible. Many leaders want to avoid controversy, escape awkward situations, and refrain from providing candid opinions.\n\nYou can't calm the storm, so stop trying. What you can do is calm yourself. The storm will pass. ~ Timber Hawkeye\n\nHigh-performing teams thrive on trust, transparency, and open discussions aimed at problem-solving. Encouraging employees to express thoughts freely and assuring them their views will be heard fosters engagement, psychological safety, self-confidence, and ownership. Leaders can contribute by establishing ground rules, facilitating conflict resolution, encouraging evidence-based arguments, and developing clear strategies and deadlines for the team's future.",
      "wordCount": 326
    },
    {
      "title": "Exclusion and marginalization attack employees' sense of worth",
      "text": "Exclusion may have a negative impact on anxiety levels. Since humans have a strong urge to belong, fear of missing out on social connection because of exclusion or segregation may affect mental well-being. Many individuals, particularly those of minority ethnicity or sexual orientation, have experienced marginalization within their team.\n\nIdentifying individuals who may feel marginalized or excluded — particularly when remote work is involved — is crucial for effective leadership. Find out who is often cut off during group discussions or who avoids eye contact. The best method to understand what is going on is having regular personal conversations.\n\nLeaders can address marginalization by ensuring all team members have the opportunity to participate and have their voices heard in a calm, structured manner during meetings. Pairing new recruits with welcoming colleagues and dedicating time in each meeting to acknowledge individual contributions also aids in combating marginalization.\n\nOne of the easiest and most successful methods to urge workers to become more inclusive is to express appreciation. Positive reinforcement results in large increases in team effectiveness and dramatically lowers group members' anxiety levels.\n\nLeaders do not appreciate employees for a job well done nearly as often or as efficiently as they should. Gratitude can encourage a healthy work environment and promote self-worth among employees. Teammates in the greatest cultures have each other's backs and spend more time appreciating one another.\n\nWorkers need frequent, personalized praise to stay on track since people realize their full potential better when encouraged.\n\nGratitude should be expressed promptly after an accomplishment to help calm nervous thoughts. When team members work excellently and then get no feedback for days or weeks, they may become concerned. Leaders should express thankfulness as soon as they see wonderful things happening to promote appropriate behaviors.",
      "wordCount": 293
    },
    {
      "title": "Conclusion",
      "text": "Anxiety often leads to depression, which is why we must pay greater attention to the negative consequences of this condition. Considering how much is going on in our environment, getting overwhelmed and mentally exhausted is very easy. We live in a time where doing our best may not be enough unless we go the additional mile to make a difference. As a result, many of us are overworked, underpaid, and overburdened.\n\nMany individuals are dissatisfied with their work because of stress, and this needs to change. When it comes to anxiety, handle it as seriously as possible — and the bulk of the work falls to leaders and managers. There must be more inclusion, gratitude, encouragement, feedback, and professional assistance so workers can succeed. These practices make a workplace more relaxing and less dismal. When leaders match incentives with performance levels, they help worried employees make more positive assumptions about their jobs and abilities. Verbal praise suits small steps ahead; larger accomplishments need concrete incentives delivered quickly to be considered.\n\nTry this\n\nEmployers and leaders should adopt the Employee Assistance Program (EAP). For employees with personal or work-related issues, the EAP provides free and confidential assessments and short-term counseling as well as referrals and follow-up services.\n\nEmployees should also be appreciated with rewards and bonuses for jobs well done.\n\nRead it till the end?",
      "wordCount": 224
    }
  ],
  "totalWords": 1937
}
